kern_comm_lib/__init__.py
kern_comm_lib/base/__init__.py
kern_comm_lib/base/status.py
kern_comm_lib/base/status_code.py
kern_comm_lib/base/status_or.py
kern_comm_lib/os/__init__.py
kern_comm_lib/os/platform_vars.py
kern_comm_lib-0.0.2.dist-info/LICENSE
kern_comm_lib-0.0.2.dist-info/METADATA
kern_comm_lib-0.0.2.dist-info/WHEEL
kern_comm_lib-0.0.2.dist-info/RECORD
