Metadata-Version: 2.3
Name: kern-comm-lib
Version: 0.0.2
Summary: Kern: A collection of robust, foundational Python utilities for building reliable and maintainable applications.
License: BSD-3-Clause
Author: Martin Urban
Author-email: martin.urban@studmail.w-hs.de
Requires-Python: >=3.10
Classifier: License :: OSI Approved :: BSD License
Classifier: Programming Language :: Python :: 3
Classifier: Programming Language :: Python :: 3.10
Classifier: Programming Language :: Python :: 3.11
Classifier: Programming Language :: Python :: 3.12
Classifier: Programming Language :: Python :: 3.13
Project-URL: Homepage, https://github.com/urban233/kern-comm-lib
Project-URL: Repository, https://github.com/urban233/kern-comm-lib
